SignExtender.v
/**
 * When ctrl is 000, output I-Type
 * When ctrl is 001, output D-Type
 * When ctrl is 010, output B
 * When ctrl is 011, output CBZ
 * When ctrl is 100, output MOVZ
 */
module SignExtender(BusImm, Imm26, Ctrl);
    // Define I/O
    output reg	[63:0] BusImm;
    input	[25:0] Imm26;
    input	[2:0] Ctrl;

    // Describe sign extender, 
    // Each type's equation based on location of immediate/addr in instr
    // Addresses (B & CBZ) are also left shifted by 2 bits
    always@(*)
	case(Ctrl)
	    3'b000: BusImm = {52'b0, Imm26[21:10]}; // I-Type
	    3'b001: BusImm = {{55{Imm26[20]}}, Imm26[20:12]}; // D-Type
	    3'b010: begin 
		BusImm = {{36{Imm26[25]}}, Imm26[25:0], 2'b00}; // B
//		#0 $display("\tB found, passing 0x%h to BusImm", BusImm);
	    end
	    3'b011: begin
		BusImm = {{43{Imm26[23]}}, Imm26[23:5], 2'b00}; // CBZ
//		#0 $display("\tCBZ found, passing 0x%h to BusImm", BusImm);
	    end
	    3'b100: begin
		BusImm = {48'b0,Imm26[20:5]};
//		#0 $display("\tMOVZ found, passing 0x%h", BusImm);
	    end
	endcase
endmodule

RegisterFile.v
`timescale 1ns / 1ps

module RegisterFile(BusA, BusB, BusW, RA, RB, RW, RegWr, Clk);
    // Define I/O
    output  reg [63:0] BusA;
    output  reg [63:0] BusB;
    input   [63:0] BusW;
    input   [4:0] RA, RB, RW;
    input   RegWr;
    input   Clk;
    
    // Have 32 registers array, each 64 bits wide
    reg     [63:0] registers [31:0];
    
    // Init all registers as zero
    integer i;
    initial
        for(i = 0; i < 32; i++)
            registers[i] = 0;
     
    // Always update buses A and B on pos edge following 2 tick delay
    always@ (*) begin
        BusA <= #2 registers[RA];
        //$display("X%0d = 0x%0x", RA, registers[RA]);
        BusB <= #2 registers[RB];
    end
     
    always@ (negedge Clk) begin
        if(RegWr) begin // On falling edge, if RegWr is high update reg RW
            registers[RW] <= #3 BusW; // Delay 3 ticks on write
//            #0 $display("\tUpdating X%0d with val 0x%0x", RW, BusW);
        end
        registers[31] <= #3 0; // Register 31 is always zero
    end
endmodule

Before MOVZ/DataMemory.v
`timescale 1ns / 1ps

`define SIZE 1024

module DataMemory(ReadData , Address , WriteData , MemoryRead , MemoryWrite , Clock);
    input [63:0]      WriteData;
    input [63:0]      Address;
    input             Clock, MemoryRead, MemoryWrite;
    output reg [63:0] ReadData;

    reg [7:0]         memBank [`SIZE-1:0];


    // This task is used to write arbitrary data to the Data Memory by
    // the intialization block.
    task initset;
      input [63:0] addr;
      input [63:0] data;
      begin
     memBank[addr] =  data[63:56] ; // Big-endian for the win...
     memBank[addr+1] =  data[55:48];
     memBank[addr+2] =  data[47:40];
     memBank[addr+3] =  data[39:32];
     memBank[addr+4] =  data[31:24];
     memBank[addr+5] =  data[23:16];
     memBank[addr+6] =  data[15:8];
     memBank[addr+7] =  data[7:0];
      end
    endtask


    initial
    begin
        // preseting some data in the data memory used by test #1

        // Address 0x0 gets 0x1
        initset( 64'h0,  64'h1);  //Counter variable
        initset( 64'h8,  64'ha);  //Part of mask
        initset( 64'h10, 64'h5);  //Other part of mask
        initset( 64'h18, 64'h0ffbea7deadbeeff); //big constant
        initset( 64'h20, 64'h0); //clearing space

        // Add any data you need for your tests here.

    end

    // This always block reads the data memory and places a double word
    // on the ReadData bus.
    always @(posedge Clock)
    begin
        if(MemoryRead)
        begin
            ReadData[63:56] <= #20 memBank[Address];
            ReadData[55:48] <= #20 memBank[Address+1];
            ReadData[47:40] <= #20 memBank[Address+2];
            ReadData[39:32] <= #20 memBank[Address+3];
            ReadData[31:24] <= #20 memBank[Address+4];
            ReadData[23:16] <= #20 memBank[Address+5];
            ReadData[15:8] <= #20 memBank[Address+6];
            ReadData[7:0] <= #20 memBank[Address+7];
//            $display("Just read 0x%h from address ", ReadData, Address);
        end
    end

    // This always block takes data from the WriteData bus and writes
    // it into the DataMemory.
    always @(posedge Clock)
    begin
        if(MemoryWrite)
        begin
            memBank[Address] <= #20 WriteData[63:56] ;
            memBank[Address+1] <= #20 WriteData[55:48];
            memBank[Address+2] <= #20 WriteData[47:40];
            memBank[Address+3] <= #20 WriteData[39:32];
            memBank[Address+4] <= #20 WriteData[31:24];
            memBank[Address+5] <= #20 WriteData[23:16];
            memBank[Address+6] <= #20 WriteData[15:8];
            memBank[Address+7] <= #20 WriteData[7:0];
            // Could be useful for debugging:
//             $display("Writing Address:%h Data:%h",Address, WriteData);
        end
    end
endmodule

NextPCLogic.v
`timescale 1ns / 1ps

module NextPCLogic(NextPC, CurrentPC, SignExtImm64, Branch, ALUZero, Uncondbranch);
	// Declare I/O
	output reg [63:0] NextPC;
	input [63:0] CurrentPC, SignExtImm64; // SignExtImm64 is output of Sign Extender from previous lab
	input Branch, ALUZero, Uncondbranch;
	
	// Declare internal wires
	reg [63:0] PCPlusFour, ALUResult;
	
	/**
	 * Describe PCLogic based on diagram in class notes,
	 * including specified delays 
	 */
	 always@(*) begin
		// Calculate both, even though only one result will be used,
		// for realism
		PCPlusFour <= #1 CurrentPC + 4;
		ALUResult <= #2 CurrentPC + SignExtImm64;
		
		if(Uncondbranch || Branch && ALUZero) begin // Simulate MUX with ctrl sig logic
			NextPC <= #1 ALUResult; // Here #1 is MUX delay
//			$display("\tBRANCHING: curPC = 0x%h, signExt = 0x%h, going to 0x%h", CurrentPC, SignExtImm64, ALUResult);
		end else
			NextPC <= #1 PCPlusFour;
	end
endmodule

ALU.v
`define AND   4'b0000
`define OR    4'b0001
`define ADD   4'b0010
`define SUB   4'b0110
`define PassB 4'b0111
`define MOVZ  4'b1??0

`timescale 1ns / 1ps

module ALU(BusW, BusA, BusB, ALUCtrl, Zero);
    
    parameter n = 64;

    output  [n-1:0] BusW;
    input   [n-1:0] BusA, BusB;
    input   [3:0] ALUCtrl;
    output  Zero;
    
    reg     [n-1:0] BusW;
    
    // Always at an input change,
    // calculate BusW with basic ALU functions, selected by the ALUCtrl.
    always @(ALUCtrl or BusA or BusB) begin
//        $display("ALUCtrl is %b", ALUCtrl);
        casez(ALUCtrl)
            `AND:   BusW <= #20 BusA & BusB;
            `OR:    BusW <= #20 BusA | BusB;
            `ADD:   BusW <= #20 BusA + BusB;
            `SUB:   BusW <= #20 BusA - BusB;
            `MOVZ:  BusW <= #20 BusB << ALUCtrl[2:1] * 16;
            `PassB: BusW <= #20 BusB;
        endcase
    end

    assign #1 Zero = !BusW ? 1 : 0;
endmodule

SingleCycleControl.v
`define OPCODE_ANDREG 11'b?0001010???
`define OPCODE_ORRREG 11'b?0101010???
`define OPCODE_ADDREG 11'b?0?01011???
`define OPCODE_SUBREG 11'b?1?01011???

`define OPCODE_ADDIMM 11'b?0?10001???
`define OPCODE_SUBIMM 11'b?1?10001???

`define OPCODE_MOVZ   11'b110100101??

`define OPCODE_B      11'b?00101?????
`define OPCODE_CBZ    11'b?011010????

`define OPCODE_LDUR   11'b??111000010
`define OPCODE_STUR   11'b??111000000

module control(
    output reg reg2loc,
    output reg alusrc,
    output reg mem2reg,
    output reg regwrite,
    output reg memread,
    output reg memwrite,
    output reg branch,
    output reg uncond_branch,
    output reg [3:0] aluop,
    output reg [2:0] signop,
    input [10:0] opcode
);

always @(*) begin
    casez (opcode)
        `OPCODE_LDUR: begin
            reg2loc       <= 1'bx;
            alusrc        <= 1'b1;
            mem2reg       <= 1'b1;
            regwrite      <= 1'b1;
            memread       <= 1'b1;
            memwrite      <= 1'b0;
            branch        <= 1'b0;
            uncond_branch <= 1'b0;
            aluop         <= 4'b0010;
            signop        <= 3'b001;
        end
        `OPCODE_STUR: begin
            reg2loc       <= 1'b1;
            alusrc        <= 1'b1;
            mem2reg       <= 1'bx;
            regwrite      <= 1'b0;
            memread       <= 1'b0;
            memwrite      <= 1'b1;
            branch        <= 1'b0;
            uncond_branch <= 1'b0;
            aluop         <= 4'b0010;
            signop        <= 3'b001;
        end
        `OPCODE_ADDREG: begin
            reg2loc       <= 1'b0;
            alusrc        <= 1'b0;
            mem2reg       <= 1'b0;
            regwrite      <= 1'b1;
            memread       <= 1'b0;
            memwrite      <= 1'b0;
            branch        <= 1'b0;
            uncond_branch <= 1'b0;
            aluop         <= 4'b0010;
            signop        <= 3'bxxx;
        end
        `OPCODE_ADDIMM: begin
            reg2loc       <= 1'b0;
            alusrc        <= 1'b1;
            mem2reg       <= 1'b0;
            regwrite      <= 1'b1;
            memread       <= 1'b0;
            memwrite      <= 1'b0;
            branch        <= 1'b0;
            uncond_branch <= 1'b0;
            aluop         <= 4'b0010;
            signop        <= 3'b000;
        end
        `OPCODE_SUBREG: begin
            reg2loc       <= 1'b0;
            alusrc        <= 1'b0;
            mem2reg       <= 1'b0;
            regwrite      <= 1'b1;
            memread       <= 1'b0;
            memwrite      <= 1'b0;
            branch        <= 1'b0;
            uncond_branch <= 1'b0;
            aluop         <= 4'b0110;
            signop        <= 3'bxxx;
        end
        `OPCODE_SUBIMM: begin
            reg2loc       <= 1'b0;
            alusrc        <= 1'b1;
            mem2reg       <= 1'b0;
            regwrite      <= 1'b1;
            memread       <= 1'b0;
            memwrite      <= 1'b0;
            branch        <= 1'b0;
            uncond_branch <= 1'b0;
            aluop         <= 4'b0110;
            signop        <= 3'b000;
        end
        `OPCODE_ANDREG: begin
            reg2loc       <= 1'b0;
            alusrc        <= 1'b0;
            mem2reg       <= 1'b0;
            regwrite      <= 1'b1;
            memread       <= 1'b0;
            memwrite      <= 1'b0;
            branch        <= 1'b0;
            uncond_branch <= 1'b0;
            aluop         <= 4'b0000;
            signop        <= 3'bxxx;
        end
        `OPCODE_ORRREG: begin
            reg2loc       <= 1'b0;
            alusrc        <= 1'b0;
            mem2reg       <= 1'b0;
            regwrite      <= 1'b1;
            memread       <= 1'b0;
            memwrite      <= 1'b0;
            branch        <= 1'b0;
            uncond_branch <= 1'b0;
            aluop         <= 4'b0001;
            signop        <= 3'bxxx;
        end
        `OPCODE_CBZ: begin
            reg2loc       <= 1'b1;
            alusrc        <= 1'b0;
            mem2reg       <= 1'bx;
            regwrite      <= 1'b0;
            memread       <= 1'b0;
            memwrite      <= 1'b0;
            branch        <= 1'b1;
            uncond_branch <= 1'b0;
            aluop         <= 4'b0111;
            signop        <= 3'b011;
        end
        `OPCODE_B: begin
            reg2loc       <= 1'bx;
            alusrc        <= 1'bx;
            mem2reg       <= 1'bx;
            regwrite      <= 1'b0;
            memread       <= 1'b0;
            memwrite      <= 1'b0;
            branch        <= 1'b0;
            uncond_branch <= 1'b1;
            aluop         <= 4'bxxxx;
            signop        <= 3'b010;
        end
        `OPCODE_MOVZ: begin
            //#0 $display("\tExecuting MOVZ instruction, aluop = %b.", {1'b1, opcode[1:0], 1'b0});
            reg2loc       <= 1'bx;
            alusrc        <= 1'b1;
            mem2reg       <= 1'b0;
            regwrite      <= 1'b1;
            memread       <= 1'bx;
            memwrite      <= 1'b0;
            branch        <= 1'b0;
            uncond_branch <= 1'b0;
            aluop         <= {1'b1, opcode[1:0], 1'b0};
            signop        <= 3'b100;
        end
        default: begin
            reg2loc       <= 1'bx;
            alusrc        <= 1'bx;
            mem2reg       <= 1'bx;
            regwrite      <= 1'b0;
            memread       <= 1'b0;
            memwrite      <= 1'b0;
            branch        <= 1'b0;
            uncond_branch <= 1'b0;
            aluop         <= 4'bxxxx;
            signop        <= 3'bxxx;
        end
    endcase
end

endmodule

InstructionMemory-1.v
`timescale 1ns / 1ps
/*
 * Module: InstructionMemory
 *
 * Implements read-only instruction memory
 * 
 */
module InstructionMemory(Data, Address);
   parameter T_rd = 20;
   parameter MemSize = 40;
   
   output [31:0] Data;
   input [63:0]  Address;
   reg [31:0] 	 Data;
   
   /*
    * ECEN 350 Processor Test Functions
    * Texas A&M University
    */
   
   always @ (Address) begin
      #4;
      case(Address)

	/* Test Program 1:
	 * Program loads constants from the data memory. Uses these constants to test
	 * the following instructions: LDUR, ORR, AND, CBZ, ADD, SUB, STUR and B.
	 * 
	 * Assembly code for test:
	 * 
	 * 0: LDUR X9, [XZR, 0x0]    //Load 1 into x9
	 * 4: LDUR X10, [XZR, 0x8]   //Load a into x10
	 * 8: LDUR X11, [XZR, 0x10]  //Load 5 into x11
	 * C: LDUR X12, [XZR, 0x18]  //Load big constant into x12
	 * 10: LDUR X13, [XZR, 0x20]  //load a 0 into X13
	 * 
	 * 14: ORR X10, X10, X11  //Create mask of 0xf
	 * 18: AND X12, X12, X10  //Mask off low order bits of big constant
	 * 
	 * loop:
	 * 1C: CBZ X12, end  //while X12 is not 0
	 * 20: ADD X13, X13, X9  //Increment counter in X13
	 * 24: SUB X12, X12, X9  //Decrement remainder of big constant in X12
	 * 28: B loop  //Repeat till X12 is 0
	 * 2C: STUR X13, [XZR, 0x20]  //store back the counter value into the memory location 0x20
	 * 30: LDUR X13, [XZR, 0x20]
	 */
	

	63'h000: Data = 32'hF84003E9;
	63'h004: Data = 32'hF84083EA;
	63'h008: Data = 32'hF84103EB;
	63'h00c: Data = 32'hF84183EC;
	63'h010: Data = 32'hF84203ED;
	63'h014: Data = 32'hAA0B014A;
	63'h018: Data = 32'h8A0A018C;
	63'h01c: Data = 32'hB400008C;
	63'h020: Data = 32'h8B0901AD;
	63'h024: Data = 32'hCB09018C;
	63'h028: Data = 32'h17FFFFFD;
	63'h02c: Data = 32'hF80203ED;
	63'h030: Data = 32'hF84203ED;  //One last load to place stored value on memdbus for test checking.

	/* Add code for your tests here */
	63'h034: Data = 32'hD2E24689; // MOV 0x1234 << 3*16 into X9
	63'h038: Data = 32'hD2CaCF0A; // MOV 0x5678 << 2*16 into X10
	63'h03c: Data = 32'hAA0A0129; // X9 = X9 ORR X10 (combines current 2 movz's into X9)
	63'h040: Data = 32'hD2B3578A; // MOV 0x9abc << 1*16 into X10
	63'h044: Data = 32'hAA0A0129; // X9 = X9 ORR X10 (combines current 3 movz's into X9)
	63'h048: Data = 32'hD29BDE0A; // MOV 0xdef0 << 0*16 into X10
	63'h04c: Data = 32'hAA0A0129; // X9 = X9 ORR X10 (combines all movz's into X9)
	63'h050: Data = 32'hF801C3E9; // STUR X9, [XZR, 0x28]
	63'h054: Data = 32'hF841C3E9; // LDUR X10, [XZR, 0x28]
			
	default: Data = 32'hXXXXXXXX;
      endcase
   end
endmodule

SingleCycleProc.v
module singlecycle(
    input resetl,
    input [63:0] startpc,
    output reg [63:0] currentpc,
    output [63:0] dmemout,
    input CLK
);

    // Next PC connections
    wire [63:0] nextpc;       // The next PC, to be updated on clock cycle

    // Instruction Memory connections
    wire [31:0] instruction;  // The current instruction

    // Parts of instruction
    wire [4:0] rd;            // The destination register
    wire [4:0] rm;            // Operand 1
    wire [4:0] rn;            // Operand 2
    wire [10:0] opcode;

    // Control wires
    wire reg2loc;
    wire alusrc;
    wire mem2reg;
    wire regwrite;
    wire memread;
    wire memwrite;
    wire branch;
    wire uncond_branch;
    wire [3:0] aluctrl;
    wire [2:0] signop;

    // Register file connections
    wire [63:0] regoutA;     // Output A
    wire [63:0] regoutB;     // Output B

    // ALU connections
    wire [63:0] aluout;
    wire zero;

    // Sign Extender connections
    wire [63:0] extimm;

    // PC update logic
    always @(negedge CLK)
    begin
        if (resetl)
            currentpc <= nextpc;
        else
            currentpc <= startpc;
    end

    // Parts of instruction
    assign rd = instruction[4:0];
    assign rm = instruction[9:5];
    assign rn = reg2loc ? instruction[4:0] : instruction[20:16];
    assign opcode = instruction[31:21];

    InstructionMemory imem(
        .Data(instruction),
        .Address(currentpc)
    );

    control control(
        .reg2loc(reg2loc),
        .alusrc(alusrc),
        .mem2reg(mem2reg),
        .regwrite(regwrite),
        .memread(memread),
        .memwrite(memwrite),
        .branch(branch),
        .uncond_branch(uncond_branch),
        .aluop(aluctrl),
        .signop(signop),
        .opcode(opcode)
    );

    /*
    * Connect the remaining datapath elements below.
    * Do not forget any additional multiplexers that may be required.
    */
    ALU alu(
        .BusW(aluout), 
        .BusA(regoutA), 
        .BusB(alusrc ? extimm : regoutB), // If alusrc use sign ext result, else use regoutB
        .ALUCtrl(aluctrl), 
        .Zero(zero)
    );
    
    NextPCLogic pcLogic(
        .NextPC(nextpc), 
        .CurrentPC(currentpc), 
        .SignExtImm64(extimm), 
        .Branch(branch), 
        .ALUZero(zero), 
        .Uncondbranch(uncond_branch)
    );
    
    DataMemory mem(
        .ReadData(dmemout), 
        .Address(aluout), 
        .WriteData(regoutB), 
        .MemoryRead(memread), 
        .MemoryWrite(memwrite), 
        .Clock(CLK)
    );
    
    RegisterFile regs(
        .BusA(regoutA), 
        .BusB(regoutB), 
        .BusW(mem2reg ? dmemout : aluout),  // If mem2reg use output of mem, else use aluout
        .RA(rm), 
        .RB(rn), 
        .RW(rd), 
        .RegWr(regwrite), 
        .Clk(CLK)
    );
    
    SignExtender signext(
        .BusImm(extimm), 
        .Imm26(instruction[25:0]), 
        .Ctrl(signop)
    );

endmodule

SingleCycleProcTest.v
`timescale 1ns / 1ps

`define STRLEN 32
`define HalfClockPeriod 60
`define ClockPeriod `HalfClockPeriod * 2

module SingleCycleProcTest_v;

    initial
    begin
        $dumpfile("singlecycle.vcd");
        $dumpvars;
    end

    // These tasks are used to check if a given test has passed and
    // confirm that all tests passed.
    task passTest;
        input [63:0] actualOut, expectedOut;
        input [`STRLEN*8:0] testType;
        inout [7:0] 	  passed;

        if(actualOut == expectedOut) begin $display ("%s passed", testType); passed = passed + 1; end
        else $display ("%s failed: 0x%x should be 0x%x", testType, actualOut, expectedOut);
    endtask

    task allPassed;
        input [7:0] passed;
        input [7:0] numTests;

        if(passed == numTests) $display ("All tests passed");
        else $display("Some tests failed: %d of %d passed", passed, numTests);
    endtask

    // Inputs
    reg        CLK;
    reg        Reset_L;
    reg [63:0] startPC;
    reg [7:0]  passed;
    reg [15:0] watchdog;

    // Outputs
    wire [63:0] dMemOut;
    wire [63:0] currentPC;

    // Instantiate the Unit Under Test (UUT)
    singlecycle uut (
        .CLK(CLK),
        .resetl(Reset_L),
        .startpc(startPC),
        .currentpc(currentPC),
        .dmemout(dMemOut)
    );

    initial begin
        // Initialize Inputs
        Reset_L = 1;
        startPC = 0;
        passed = 0;

        // Initialize Watchdog timer
        watchdog = 0;

        // Wait for global reset
        #(1 * `ClockPeriod);

        // Program 1
        #1
        Reset_L = 0; startPC = 0;
        #(1 * `ClockPeriod);
        Reset_L = 1;

        // ***********************************************************
        // This while loop will continue cycling the processor until the
        // PC reaches the final instruction in the first test.  If the
        // program forms an infinite loop, never reaching the end, the
        // watchdog timer will kick in and kill simulation after 64K
        // cycles.
        // ***********************************************************

        while (currentPC < 64'h34) begin
           #(1 * `ClockPeriod);
           $display("CurrentPC:%h",currentPC);
        end
        #(1 * `ClockPeriod);	// One more cycle to load the pass code from the DataMemory.
        passTest(dMemOut, 64'hF, "Results of Program 1", passed);

        // ***********************************************************
        // Add your new tests here
        // ***********************************************************
        while (currentPC < 64'h58) begin
           #(1 * `ClockPeriod);
           $display("CurrentPC:%h",currentPC);
        end
        #(1 * `ClockPeriod);	// One more cycle to load the pass code from the DataMemory.
        passTest(dMemOut, 64'h123456789abcdef0, "Results of MOVZ test", passed);

        // Done
        allPassed(passed, 2);   // Be sure to change the one to match
                                // the number of tests you add.
        $finish;
    end

    initial begin
        CLK = 0;
    end

    // The following is correct if clock starts at LOW level at StartTime //
    always begin
        #`HalfClockPeriod CLK = ~CLK;
        #`HalfClockPeriod CLK = ~CLK;
        watchdog = watchdog +1;
    end

    // Kill the simulation if the watchdog hits 64K cycles
    always @*
        if (watchdog == 16'h0FF)
        begin
            $display("Watchdog Timer Expired.");
            $finish;
        end


endmodule

singlecycle.vcd
$date
	Thu Dec  3 19:08:29 2020
$end
$version
	Icarus Verilog
$end
$timescale
	1ps
$end
$scope module SingleCycleProcTest_v $end
$var wire 64 ! dMemOut [63:0] $end
$var wire 64 " currentPC [63:0] $end
$var reg 1 # CLK $end
$var reg 1 $ Reset_L $end
$var reg 8 % passed [7:0] $end
$var reg 64 & startPC [63:0] $end
$var reg 16 ' watchdog [15:0] $end
$scope module uut $end
$var wire 1 # CLK $end
$var wire 1 $ resetl $end
$var wire 64 ( startpc [63:0] $end
$var wire 1 ) zero $end
$var wire 1 * uncond_branch $end
$var wire 3 + signop [2:0] $end
$var wire 5 , rn [4:0] $end
$var wire 5 - rm [4:0] $end
$var wire 1 . regwrite $end
$var wire 64 / regoutB [63:0] $end
$var wire 64 0 regoutA [63:0] $end
$var wire 1 1 reg2loc $end
$var wire 5 2 rd [4:0] $end
$var wire 11 3 opcode [10:0] $end
$var wire 64 4 nextpc [63:0] $end
$var wire 1 5 memwrite $end
$var wire 1 6 memread $end
$var wire 1 7 mem2reg $end
$var wire 32 8 instruction [31:0] $end
$var wire 64 9 extimm [63:0] $end
$var wire 64 : dmemout [63:0] $end
$var wire 1 ; branch $end
$var wire 1 < alusrc $end
$var wire 64 = aluout [63:0] $end
$var wire 4 > aluctrl [3:0] $end
$var reg 64 ? currentpc [63:0] $end
$scope module alu $end
$var wire 64 @ BusB [63:0] $end
$var wire 1 ) Zero $end
$var wire 64 A BusA [63:0] $end
$var wire 4 B ALUCtrl [3:0] $end
$var reg 64 C BusW [63:0] $end
$upscope $end
$scope module control $end
$var wire 11 D opcode [10:0] $end
$var reg 4 E aluop [3:0] $end
$var reg 1 < alusrc $end
$var reg 1 ; branch $end
$var reg 1 7 mem2reg $end
$var reg 1 6 memread $end
$var reg 1 5 memwrite $end
$var reg 1 1 reg2loc $end
$var reg 1 . regwrite $end
$var reg 3 F signop [2:0] $end
$var reg 1 * uncond_branch $end
$upscope $end
$scope module imem $end
$var wire 64 G Address [63:0] $end
$var reg 32 H Data [31:0] $end
$upscope $end
$scope module mem $end
$var wire 64 I Address [63:0] $end
$var wire 1 # Clock $end
$var wire 1 6 MemoryRead $end
$var wire 1 5 MemoryWrite $end
$var wire 64 J WriteData [63:0] $end
$var reg 64 K ReadData [63:0] $end
$scope task initset $end
$var reg 64 L addr [63:0] $end
$var reg 64 M data [63:0] $end
$upscope $end
$upscope $end
$scope module pcLogic $end
$var wire 1 ) ALUZero $end
$var wire 1 ; Branch $end
$var wire 64 N CurrentPC [63:0] $end
$var wire 1 * Uncondbranch $end
$var wire 64 O SignExtImm64 [63:0] $end
$var reg 64 P ALUResult [63:0] $end
$var reg 64 Q NextPC [63:0] $end
$var reg 64 R PCPlusFour [63:0] $end
$upscope $end
$scope module regs $end
$var wire 64 S BusW [63:0] $end
$var wire 1 # Clk $end
$var wire 5 T RA [4:0] $end
$var wire 5 U RB [4:0] $end
$var wire 5 V RW [4:0] $end
$var wire 1 . RegWr $end
$var reg 64 W BusA [63:0] $end
$var reg 64 X BusB [63:0] $end
$var integer 32 Y i [31:0] $end
$upscope $end
$scope module signext $end
$var wire 3 Z Ctrl [2:0] $end
$var wire 26 [ Imm26 [25:0] $end
$var reg 64 \ BusImm [63:0] $end
$upscope $end
$upscope $end
$scope task allPassed $end
$var reg 8 ] numTests [7:0] $end
$var reg 8 ^ passed [7:0] $end
$upscope $end
$scope task passTest $end
$var reg 64 _ actualOut [63:0] $end
$var reg 64 ` expectedOut [63:0] $end
$var reg 8 a passed [7:0] $end
$var reg 257 b testType [256:0] $end
$upscope $end
$upscope $end
$enddefinitions $end
#0
$dumpvars
bx b
bx a
bx `
bx _
bx ^
bx ]
bx \
bx [
bx Z
b100000 Y
bx X
bx W
bx V
bx U
bx T
bx S
bx R
bx Q
bx P
bx O
bx N
b0 M
b100000 L
bx K
bx J
bx I
bx H
bx G
bx F
bx E
bx D
bx C
bx B
bx A
bx @
bx ?
bx >
bx =
x<
x;
bx :
bx 9
bx 8
x7
x6
x5
bx 4
bx 3
bx 2
x1
bx 0
bx /
x.
bx -
bx ,
bx +
x*
x)
b0 (
b0 '
b0 &
b0 %
1$
0#
bx "
bx !
$end
#60000
1#
#120000
b1 '
0#
#121000
0$
#180000
1#
#240000
b0 "
b0 ?
b0 G
b0 N
b10 '
0#
#241000
b100 R
1$
#242000
b100 4
b100 Q
#244000
b0 @
b0 9
b0 O
b0 \
b1 +
b1 F
b1 Z
b10 >
b10 B
b10 E
0*
0;
05
16
1.
17
1<
b0x00x ,
b0x00x U
b10000000000001111101001 [
b11111000010 3
b11111000010 D
b11111 -
b11111 T
b1001 2
b1001 V
b11111000010000000000001111101001 8
b11111000010000000000001111101001 H
#246000
b0 P
b0 0
b0 A
b0 W
#266000
b0 =
b0 C
b0 I
#267000
1)
#300000
1#
#320000
b1 S
b1 !
b1 :
b1 K
#360000
b100 "
b100 ?
b100 G
b100 N
b11 '
0#
#361000
b1000 R
#362000
b1000 4
b1000 Q
b100 P
#364000
b1000 @
b1000 9
b1000 O
b1000 \
b0x0x0 ,
b0x0x0 U
b10000001000001111101010 [
b1010 2
b1010 V
b11111000010000001000001111101010 8
b11111000010000001000001111101010 H
#366000
b1100 P
#384000
b1000 =
b1000 C
b1000 I
#385000
0)
#420000
1#
#440000
b1010 S
b1010 !
b1010 :
b1010 K
#480000
b1000 "
b1000 ?
b1000 G
b1000 N
b100 '
0#
#481000
b1100 R
#482000
b1100 4
b1100 Q
b10000 P
#484000
b10000 @
b10000 9
b10000 O
b10000 \
b0x0x1 ,
b0x0x1 U
b10000010000001111101011 [
b1011 2
b1011 V
b11111000010000010000001111101011 8
b11111000010000010000001111101011 H
#486000
b11000 P
#504000
b10000 =
b10000 C
b10000 I
#540000
1#
#560000
b101 S
b101 !
b101 :
b101 K
#600000
b1100 "
b1100 ?
b1100 G
b1100 N
b101 '
0#
#601000
b10000 R
#602000
b10000 4
b10000 Q
b11100 P
#604000
b11000 @
b11000 9
b11000 O
b11000 \
b0xx0x ,
b0xx0x U
b10000011000001111101100 [
b1100 2
b1100 V
b11111000010000011000001111101100 8
b11111000010000011000001111101100 H
#606000
b100100 P
#624000
b11000 =
b11000 C
b11000 I
#660000
1#
#680000
b111111111011111010100111110111101010110110111110111011111111 S
b111111111011111010100111110111101010110110111110111011111111 !
b111111111011111010100111110111101010110110111110111011111111 :
b111111111011111010100111110111101010110110111110111011111111 K
#720000
b10000 "
b10000 ?
b10000 G
b10000 N
b110 '
0#
#721000
b10100 R
#722000
b10100 4
b10100 Q
b101000 P
#724000
b100000 @
b100000 9
b100000 O
b100000 \
b0xxxx ,
b0xxxx U
b10000100000001111101101 [
b1101 2
b1101 V
b11111000010000100000001111101101 8
b11111000010000100000001111101101 H
#726000
b110000 P
#744000
b100000 =
b100000 C
b100000 I
#780000
1#
#800000
b0 S
b0 !
b0 :
b0 K
#840000
b10100 "
b10100 ?
b10100 G
b10100 N
b111 '
0#
#841000
b11000 R
#842000
b11000 4
b11000 Q
b110100 P
#844000
b100000 S
bx +
bx F
bx Z
b1 >
b1 B
b1 E
06
07
0<
01
bx @
b10110000 9
b10110000 O
b10110000 \
b1011 ,
b1011 U
b10000010110000000101001010 [
b10101010000 3
b10101010000 D
b1010 -
b1010 T
b1010 2
b1010 V
b10101010000010110000000101001010 8
b10101010000010110000000101001010 H
#846000
b101 @
b101 /
b101 J
b101 X
b11000100 P
b1010 0
b1010 A
b1010 W
#864000
bx S
bx =
bx C
bx I
#865000
x)
#866000
b1111 S
b1111 =
b1111 C
b1111 I
#867000
0)
#900000
1#
#960000
b11000 "
b11000 ?
b11000 G
b11000 N
b1000 '
0#
#961000
b11100 R
#962000
b11100 4
b11100 Q
b11001000 P
#964000
b0 >
b0 B
b0 E
b1010 ,
b1010 U
b10000010100000000110001100 [
b10001010000 3
b10001010000 D
b1100 -
b1100 T
b1100 2
b1100 V
b10001010000010100000000110001100 8
b10001010000010100000000110001100 H
#965000
b1111 0
b1111 A
b1111 W
#966000
b1111 @
b1111 /
b1111 J
b1111 X
b111111111011111010100111110111101010110110111110111011111111 0
b111111111011111010100111110111101010110110111110111011111111 A
b111111111011111010100111110111101010110110111110111011111111 W
#984000
b0 S
b0 =
b0 C
b0 I
#985000
b101 S
b101 =
b101 C
b101 I
1)
#986000
b1111 S
b1111 =
b1111 C
b1111 I
0)
#1020000
1#
#1080000
b11100 "
b11100 ?
b11100 G
b11100 N
b1001 '
0#
#1081000
b100000 R
#1082000
b100000 4
b100000 Q
b11001100 P
#1084000
b10000 9
b10000 O
b10000 \
b0xxxx S
b11 +
b11 F
b11 Z
b111 >
b111 B
b111 E
1;
0.
x7
11
b1100 ,
b1100 U
b10001100 [
b10110100000 3
b10110100000 D
b100 -
b100 T
b10110100000000000000000010001100 8
b10110100000000000000000010001100 H
#1085000
b1111 0
b1111 A
b1111 W
#1086000
b101100 P
b1111 /
b1111 J
b1111 X
b0 0
b0 A
b0 W
#1140000
1#
#1200000
b100000 "
b100000 ?
b100000 G
b100000 N
b1010 '
0#
#1201000
b100100 R
#1202000
b100100 4
b100100 Q
b110000 P
#1204000
b1111 S
bx +
bx F
bx Z
b10 >
b10 B
b10 E
0;
1.
07
01
b10010000000110100 9
b10010000000110100 O
b10010000000110100 \
b1001 ,
b1001 U
b11000010010000000110101101 [
b10001011000 3
b10001011000 D
b1101 -
b1101 T
b1101 2
b1101 V
b10001011000010010000000110101101 8
b10001011000010010000000110101101 H
#1206000
b1 @
b10010000001010100 P
b1 /
b1 J
b1 X
#1226000
b1 S
b1 =
b1 C
b1 I
#1260000
1#
#1320000
b100100 "
b100100 ?
b100100 G
b100100 N
b1011 '
0#
#1321000
b101000 R
#1322000
b101000 4
b101000 Q
b10010000001011000 P
#1324000
b110 >
b110 B
b110 E
b11000010010000000110001100 [
b11001011000 3
b11001011000 D
b1100 -
b1100 T
b1100 2
b1100 V
b11001011000010010000000110001100 8
b11001011000010010000000110001100 H
#1325000
b1 0
b1 A
b1 W
#1326000
b1111 0
b1111 A
b1111 W
